cpsk/__init__.py
cpsk/drive.py
cpsk/enums.py
cpsk/line.py
cpsk/parser.py
cpsk/settings.py
cpsk-0.2.2.dist-info/LICENSE
cpsk-0.2.2.dist-info/METADATA
cpsk-0.2.2.dist-info/WHEEL
cpsk-0.2.2.dist-info/top_level.txt
cpsk-0.2.2.dist-info/RECORD
