Metadata-Version: 2.1
Name: cpsk
Version: 0.2.2
Summary: an unofficial api for grabbing data from cp.sk
Home-page: https://github.com/Adman/python-cpsk-api
Author: Adrian Matejov
Author-email: a.matejov@centrum.sk
License: The MIT License (MIT)
Keywords: travel,train,bus
License-File: LICENSE
Requires-Dist: requests
Requires-Dist: lxml
